napari_segment_anything_2/__init__.py
napari_segment_anything_2/_widget.py
napari_segment_anything_2/napari.yaml
napari_segment_anything_2/sam2.py
napari_segment_anything_2/utils.py
napari_segment_anything_2/_tests/__init__.py
napari_segment_anything_2/_tests/test_widget.py
napari_segment_anything_2/configs/__init__.py
napari_segment_anything_2/configs/sam2_hiera_b+.yaml
napari_segment_anything_2/configs/sam2_hiera_l.yaml
napari_segment_anything_2/configs/sam2_hiera_s.yaml
napari_segment_anything_2/configs/sam2_hiera_t.yaml
napari_segment_anything_2-0.0.1.dist-info/METADATA
napari_segment_anything_2-0.0.1.dist-info/WHEEL
napari_segment_anything_2-0.0.1.dist-info/entry_points.txt
napari_segment_anything_2-0.0.1.dist-info/licenses/LICENSE
napari_segment_anything_2-0.0.1.dist-info/RECORD
