Metadata-Version: 2.3
Name: napari-segment-anything-2
Version: 0.0.1
Summary: A napari plugin for Meta's Segment Anything 2 in Images and Videos
Project-URL: Bug Tracker, https://github.com/JoOkuma/napari-segment-anything-2/issues
Project-URL: Documentation, https://github.com/JoOkuma/napari-segment-anything-2#README.md
Project-URL: Source Code, https://github.com/JoOkuma/napari-segment-anything-2
Project-URL: User Support, https://github.com/JoOkuma/napari-segment-anything-2/issues
Author: Jordão Bragantini
Author-email: jordao.bragantini@czbiohub.org
License: 
License-File: LICENSE
Classifier: Development Status :: 2 - Pre-Alpha
Classifier: Framework :: napari
Classifier: Intended Audience :: Developers
Classifier: License :: OSI Approved :: BSD License
Classifier: Operating System :: OS Independent
Classifier: Programming Language :: Python
Classifier: Programming Language :: Python :: 3
Classifier: Programming Language :: Python :: 3 :: Only
Classifier: Programming Language :: Python :: 3.9
Classifier: Programming Language :: Python :: 3.10
Classifier: Programming Language :: Python :: 3.11
Classifier: Programming Language :: Python :: 3.12
Classifier: Topic :: Scientific/Engineering :: Image Processing
Requires-Python: >=3.9
Requires-Dist: magicgui
Requires-Dist: numpy
Requires-Dist: qtpy
Requires-Dist: scikit-image
Provides-Extra: testing
Requires-Dist: napari; extra == 'testing'
Requires-Dist: pyqt5; extra == 'testing'
Requires-Dist: pytest; extra == 'testing'
Requires-Dist: pytest-cov; extra == 'testing'
Requires-Dist: pytest-qt; extra == 'testing'
Requires-Dist: tox; extra == 'testing'
